rivescript_coverage_plugin/__init__.py
rivescript_coverage_plugin/plugin.py
rivescript_coverage_plugin-1.1.0.dist-info/AUTHORS.rst
rivescript_coverage_plugin-1.1.0.dist-info/LICENSE
rivescript_coverage_plugin-1.1.0.dist-info/METADATA
rivescript_coverage_plugin-1.1.0.dist-info/WHEEL
rivescript_coverage_plugin-1.1.0.dist-info/top_level.txt
rivescript_coverage_plugin-1.1.0.dist-info/RECORD
