Metadata-Version: 2.1
Name: rivescript-coverage-plugin
Version: 1.1.0
Summary: A plug-in to measure code coverage in RiveScript with python
Home-page: https://github.com/snoopyjc/rivescript_coverage_plugin
Author: Joe Cool
Author-email: snoopyjc@gmail.com
License: MIT
Keywords: rivescript_coverage_plugin
Platform: UNKNOWN
Classifier: Development Status :: 5 - Production/Stable
Classifier: Intended Audience :: Developers
Classifier: License :: OSI Approved :: MIT License
Classifier: Natural Language :: English
Classifier: Programming Language :: Python :: 3.6
Classifier: Programming Language :: Python :: 3.7
Classifier: Programming Language :: Python :: Implementation :: PyPy
Requires-Dist: coverage (>=5.0)
Requires-Dist: rivescript (>=1.14.9)
